[
  {
    "Title": "4x African Footballer of the Year",
    "Year": "2010",
    "Club": "Inter Milan"
  },
  {
    "Title": "4x African Footballer of the Year",
    "Year": "2005",
    "Club": "FC Barcelona"
  },
  {
    "Title": "4x African Footballer of the Year",
    "Year": "2004",
    "Club": "RCD Mallorca"
  },
  {
    "Title": "4x African Footballer of the Year",
    "Year": "2003",
    "Club": "RCD Mallorca"
  },
  {
    "Title": "4x Top goal scorer",
    "Year": "10/11",
    "Club": "Italy Cup\n                                                     - 5 Goals"
  },
  {
    "Title": "4x Top goal scorer",
    "Year": "07/08",
    "Club": "Africa Cup of Nations\n                                                     - 5 Goals"
  },
  {
    "Title": "4x Top goal scorer",
    "Year": "05/06",
    "Club": "LaLiga\n                                                     - 26 Goals"
  },
  {
    "Title": "4x Top goal scorer",
    "Year": "05/06",
    "Club": "Africa Cup of Nations\n                                                     - 5 Goals"
  },
  {
    "Title": "2x Africa Cup winner",
    "Year": "2002",
    "Club": "Cameroon"
  },
  {
    "Title": "2x Africa Cup winner",
    "Year": "2000",
    "Club": "Cameroon"
  },
  {
    "Title": "4x Champions League winner",
    "Year": "09/10",
    "Club": "Inter Milan"
  },
  {
    "Title": "4x Champions League winner",
    "Year": "08/09",
    "Club": "FC Barcelona"
  },
  {
    "Title": "4x Champions League winner",
    "Year": "05/06",
    "Club": "FC Barcelona"
  },
  {
    "Title": "4x Champions League winner",
    "Year": "99/00",
    "Club": "Real Madrid"
  },
  {
    "Title": "1x FIFA Club World Cup winner",
    "Year": "2011",
    "Club": "Inter Milan"
  },
  {
    "Title": "3x Spanish champion",
    "Year": "08/09",
    "Club": "FC Barcelona"
  },
  {
    "Title": "3x Spanish champion",
    "Year": "05/06",
    "Club": "FC Barcelona"
  },
  {
    "Title": "3x Spanish champion",
    "Year": "04/05",
    "Club": "FC Barcelona"
  },
  {
    "Title": "1x Italian champion",
    "Year": "09/10",
    "Club": "Inter Milan"
  },
  {
    "Title": "2x Spanish cup winner",
    "Year": "08/09",
    "Club": "FC Barcelona"
  },
  {
    "Title": "2x Spanish cup winner",
    "Year": "02/03",
    "Club": "RCD Mallorca"
  },
  {
    "Title": "2x Italian cup winner",
    "Year": "10/11",
    "Club": "Inter Milan"
  },
  {
    "Title": "2x Italian cup winner",
    "Year": "09/10",
    "Club": "Inter Milan"
  },
  {
    "Title": "1x Italian Super Cup winner",
    "Year": "10/11",
    "Club": "Inter Milan"
  },
  {
    "Title": "2x Spanish Super Cup winner",
    "Year": "06/07",
    "Club": "FC Barcelona"
  },
  {
    "Title": "2x Spanish Super Cup winner",
    "Year": "05/06",
    "Club": "FC Barcelona"
  },
  {
    "Title": "1x Olympic medalist",
    "Year": "2000",
    "Club": "Cameroon"
  },
  {
    "Title": "2x Copa Catalunya winner",
    "Year": "06/07",
    "Club": "FC Barcelona"
  },
  {
    "Title": "2x Copa Catalunya winner",
    "Year": "04/05",
    "Club": "FC Barcelona"
  }
]